{
  "suma": {
    "Identificador": "suma",
    "Categor\u00eda": "IDENTIFICADOR",
    "Tipo": "variable",
    "\u00c1mbito": "Local",
    "Direcci\u00f3n": "0x35DE40C6CAF473AF",
    "L\u00ednea": "2",
    "Valor": "No inicializado",
    "Estado": "Usado",
    "Estructura": "N/A",
    "Uso": 1
  },
  "a": {
    "Identificador": "a",
    "Categor\u00eda": "IDENTIFICADOR",
    "Tipo": "variable",
    "\u00c1mbito": "Local",
    "Direcci\u00f3n": "0x27D808FAD0708E1B",
    "L\u00ednea": "14",
    "Valor": "No inicializado",
    "Estado": "Usado",
    "Estructura": "N/A",
    "Uso": 2
  },
  "b": {
    "Identificador": "b",
    "Categor\u00eda": "IDENTIFICADOR",
    "Tipo": "variable",
    "\u00c1mbito": "Local",
    "Direcci\u00f3n": "0x57E72FCC8F3C2B87",
    "L\u00ednea": "16",
    "Valor": "No inicializado",
    "Estado": "Usado",
    "Estructura": "N/A",
    "Uso": 2
  }
}